Workbook

Sheet Income Statement
A1: Peachtree Technologies, Inc.
A2: 2026 Income Statement
A4: Revenue | B4: 5000000
A5: Cost of Goods Sold | B5: 2100000
A6: Gross Profit | B6: =B4-B5 -> 2900000
A8: Salaries & Wages | B8: 900000
A9: Depreciation Expense | B9: 250000
A10: Business Meals | B10: 80000
A11: Fines & Penalties | B11: 25000
A12: Interest Expense | B12: 120000
A13: Other Operating Expenses | B13: 625000
A14: Total Operating Expenses | B14: =SUM(B8:B13) -> 2000000
A16: Pretax Book Income | B16: =B6-B14 -> 900000

Sheet Book-Tax Recon
A1: Peachtree Technologies, Inc.
A2: 2026 Book-to-Tax Reconciliation
A4: Pretax Book Income | B4: ='Income Statement'!B16 -> 900000
A6: Book-Tax Adjustment | B6: Book Amount | C6: Tax Amount | D6: Adjustment | E6: Difference Type
A7: Business Meals | B7: ='Income Statement'!B10 -> 80000 | C7: =B7*50% -> 40000 | D7: =B7-C7 -> 40000 | E7: Permanent
A8: Fines & Penalties | B8: ='Income Statement'!B11 -> 25000 | C8: 0 | D8: =B8-C8 -> 25000 | E8: Permanent
A9: Depreciation | B9: ='Income Statement'!B9 -> 250000 | C9: 350000 | D9: =B9-C9 -> -100000 | E9: Temporary
A11: Net Book-Tax Adjustments | D11: =SUM(D7:D9) -> -35000
A13: Taxable Income | B13: =B4+D11 -> 865000

Sheet Tax Calculation
A1: Peachtree Technologies, Inc.
A2: 2026 Federal Corporate Tax Calculation
A4: Taxable Income | B4: ='Book-Tax Recon'!B13 -> 865000
A5: Federal Corporate Tax Rate | B5: 0.21
A6: Estimated Federal Income Tax | B6: =B4*B5 -> 181650
A8: Pretax Book Income | B8: ='Book-Tax Recon'!B4 -> 900000
A9: Estimated Federal Income Tax | B9: =B6 -> 181650
A10: Current Tax Rate | B10: =B9/B8 -> 0.20183333

Sheet Tax Provision
A1: Peachtree Technologies, Inc.
A2: 2026 Income Tax Provision
A4: Current Tax Provision
A5: Taxable Income | B5: ='Tax Calculation'!B4 -> 865000
A6: Federal Tax Rate | B6: ='Tax Calculation'!B5 -> 0.21
A7: Current Federal Tax Expense | B7: =B5*B6 -> 181650
A9: Deferred Tax Provision
A10: Depreciation Temporary Difference | B10: =-'Book-Tax Recon'!D9 -> 100000
A11: Federal Tax Rate | B11: ='Tax Calculation'!B5 -> 0.21
A12: Deferred Federal Tax Expense | B12: =B10*B11 -> 21000
A14: Total Income Tax Provision | B14: =B7+B12 -> 202650
A16: Pretax Book Income | B16: ='Income Statement'!B16 -> 900000
A17: Total Income Tax Provision | B17: =B14 -> 202650
A18: Effective Tax Rate | B18: =B17/B16 -> 0.22516667

Sheet Tax Research
A1: Peachtree Technologies, Inc.
A2: 2026 Tax Research & Compliance Documentation
A4: Tax Issue | B4: Research Question | C4: Conclusion | D4: Tax Treatment | E4: Authority / Source
A5: Business Meals | B5: Are ordinary business meal expenses deductible for federal income tax purposes? | C5: Generally, qualifying business meal expenses are subject to a 50% deduction limitation. | D5: 50% Deductible | E5: IRS Publication 463 / IRC §274
A6: Fines & Penalties | B6: Are fines and penalties paid to a gov't for violations of law deductible? | C6: Generally, amounts paid to a government for the violation of law are nondeductible, subject to statutory exceptions. | D6: Nondeductible under project assumption | E6: IRC §162(f)
A7: Federal Corporate Tax Rate | B7: What federal income tax rate applies to the project's C corporation? | C7: The project applies the federal corporate income tax rate to taxable income. | D7: 0.21 | E7: IRC §11
A8: Depreciation | B8: Can depreciation for tax purposes differ from depreciation recognized for financial reporting? | C8: For this model, tax depreciation is assumed to be $350,000 compared with $250,000 of book depreciation, resulting in a $100,000 temporary difference. | D8: $100,000 temporary difference | E8: IRS Publication 946 / IRC §§167-168

Sheet Dashboard
A1: Peachtree Technologies, Inc.
A2: 2026 Corporate Tax Analytics Dashboard
A5: Pretax Book Income | C5: Taxable Income | E5: Total Tax Provision | G5: Effective Tax Rate
A6: ='Income Statement'!B16 -> 900000 | C6: ='Book-Tax Recon'!B13 -> 865000 | E6: ='Tax Provision'!B14 -> 202650 | G6: ='Tax Provision'!B18 -> 0.22516667
A10: Book-to-Tax Adjustment Analysis
A12: Adjustment | B12: Amount
A13: Business Meals | B13: ='Book-Tax Recon'!D7 -> 40000
A14: Fines & Penalties | B14: ='Book-Tax Recon'!D8 -> 25000
A15: Depreciation | B15: ='Book-Tax Recon'!D9 -> -100000
A25: Tax Provision Breakdown
A27: Component | B27: Amount
A28: Current Tax Expense | B28: ='Tax Provision'!B7 -> 181650
A29: Deferred Tax Expense | B29: ='Tax Provision'!B12 -> 21000
A43: Effective Tax Rate Reconciliation
A45: Component | B45: Rate
A46: Statutory Federal Tax Rate | B46: ='Tax Calculation'!B5 -> 0.21
A47: Business Meals Impact | B47: =('Book-Tax Recon'!D7*'Tax Calculation'!B5)/'Income Statement'!B16 -> 0.0093333333
A48: Fines & Penalties Impact | B48: =('Book-Tax Recon'!D8*'Tax Calculation'!B5)/'Income Statement'!B16 -> 0.0058333333
A49: Effective Tax Rate | B49: ='Tax Provision'!B18 -> 0.22516667

Sheet Sheet7
